{
  "axes": [
    {
      "index": 0,
      "name": "Physicality",
      "partition": "ontology",
      "description": "Degree to which an entity occupies physical space and has material properties.",
      "reserved": false
    },
    {
      "index": 16,
      "name": "NumericValue",
      "partition": "computable",
      "description": "Encoded numeric value for computable concepts. Uses log-scale encoding for wide range.",
      "reserved": true
    },
    {
      "index": 17,
      "name": "NumericScale",
      "partition": "computable",
      "description": "Order of magnitude (10^n) for numeric values. Enables comparison across scales.",
      "reserved": true
    },
    {
      "index": 18,
      "name": "UnitDomain",
      "partition": "computable",
      "description": "Physical dimension category: 0=dimensionless, 1=length, 2=mass, 3=time, 4=temperature, 5=amount, 6=current, 7=luminosity.",
      "reserved": true
    },
    {
      "index": 19,
      "name": "UnitBase",
      "partition": "computable",
      "description": "Base SI unit within domain. Combined with UnitDomain to identify exact unit.",
      "reserved": true
    },
    {
      "index": 20,
      "name": "UnitPrefix",
      "partition": "computable",
      "description": "SI prefix as power of 10: -12=pico, -9=nano, -6=micro, -3=milli, 0=base, 3=kilo, 6=mega, 9=giga.",
      "reserved": true
    },
    {
      "index": 21,
      "name": "ComputeDomain",
      "partition": "computable",
      "description": "Which compute plugin handles this: 0=none, 1=math, 2=physics, 3=chemistry, 4=logic, 5=datetime.",
      "reserved": true
    },
    {
      "index": 22,
      "name": "ComputeOperationType",
      "partition": "computable",
      "description": "Type of computation: 0=none, 1=compare, 2=arithmetic, 3=convert, 4=solve, 5=balance.",
      "reserved": true
    },
    {
      "index": 23,
      "name": "ComputePrecision",
      "partition": "computable",
      "description": "Required precision level: 0=exact, 1=high, 2=medium, 3=approximate.",
      "reserved": true
    },
    {
      "index": 24,
      "name": "Existence",
      "partition": "computable",
      "description": "Epistemic status of a fact: -127=impossible, -64=unproven, 0=possible, +64=demonstrated, +127=certain. Theory facts default to +127.",
      "reserved": true
    },
    {
      "index": 1,
      "name": "Mereological",
      "partition": "ontology",
      "description": "Part-whole relationships; encodes mereological structure.",
      "reserved": false
    },
    {
      "index": 2,
      "name": "MassScale",
      "partition": "ontology",
      "description": "Rough magnitude of mass or weight on a normalized scale.",
      "reserved": false
    },
    {
      "index": 3,
      "name": "SizeScale",
      "partition": "ontology",
      "description": "Overall spatial extent or size of an entity on a normalized scale.",
      "reserved": false
    },
    {
      "index": 4,
      "name": "Temperature",
      "partition": "ontology",
      "description": "Abstracted temperature axis used for physical processes and states.",
      "reserved": false
    },
    {
      "index": 5,
      "name": "Pressure",
      "partition": "ontology",
      "description": "Abstracted pressure axis for fluids, gases, or systems under load.",
      "reserved": false
    },
    {
      "index": 6,
      "name": "Density",
      "partition": "ontology",
      "description": "Relative density or compactness of an entity or medium.",
      "reserved": false
    },
    {
      "index": 7,
      "name": "Phase",
      "partition": "ontology",
      "description": "Encodes state such as solid, liquid, gas, or plasma via discrete bands.",
      "reserved": false
    },
    {
      "index": 8,
      "name": "SpatialExtent",
      "partition": "ontology",
      "description": "Captures whether an entity is point-like, local, or extended over regions.",
      "reserved": false
    },
    {
      "index": 9,
      "name": "LocationSpecificity",
      "partition": "ontology",
      "description": "Indicates how precisely an entity or event is tied to a concrete location.",
      "reserved": false
    },
    {
      "index": 10,
      "name": "TemporalPersistence",
      "partition": "ontology",
      "description": "Distinguishes transient events from long-lived or permanent entities.",
      "reserved": false
    },
    {
      "index": 11,
      "name": "Duration",
      "partition": "ontology",
      "description": "Approximate time span for which an event or state persists.",
      "reserved": false
    },
    {
      "index": 12,
      "name": "Frequency",
      "partition": "ontology",
      "description": "How often an event or pattern recurs in a given context.",
      "reserved": false
    },
    {
      "index": 13,
      "name": "CausalityStrength",
      "partition": "ontology",
      "description": "Strength of causal influence associated with an event or relation.",
      "reserved": false
    },
    {
      "index": 14,
      "name": "DeterminismLevel",
      "partition": "ontology",
      "description": "Indicates whether a process is deterministic or stochastic in character.",
      "reserved": false
    },
    {
      "index": 15,
      "name": "Reversibility",
      "partition": "ontology",
      "description": "Degree to which a process can be reversed without loss.",
      "reserved": false
    },
    {
      "index": 48,
      "name": "LivingStatus",
      "partition": "ontology",
      "description": "Whether an entity is biologically living; high values indicate life.",
      "reserved": false
    },
    {
      "index": 49,
      "name": "SpeciesTaxonomy",
      "partition": "ontology",
      "description": "Encodes high-level biological taxonomy class for living entities.",
      "reserved": false
    },
    {
      "index": 50,
      "name": "LifeStage",
      "partition": "ontology",
      "description": "Distinguishes juvenile, adult, and senescent stages for organisms.",
      "reserved": false
    },
    {
      "index": 51,
      "name": "HealthVitality",
      "partition": "ontology",
      "description": "Measures health or vitality of living entities on a coarse scale.",
      "reserved": false
    },
    {
      "index": 58,
      "name": "CognitionBaseline",
      "partition": "ontology",
      "description": "Represents baseline cognitive capacity, such as non-sapient, animal, or human-level.",
      "reserved": false
    },
    {
      "index": 59,
      "name": "AgencyBaseline",
      "partition": "ontology",
      "description": "Indicates whether an entity can initiate actions intentionally.",
      "reserved": false
    },
    {
      "index": 80,
      "name": "ArtifactDevice",
      "partition": "ontology",
      "description": "Marks entities that are artifacts or devices rather than natural objects.",
      "reserved": false
    },
    {
      "index": 83,
      "name": "ComputationCapability",
      "partition": "ontology",
      "description": "Indicates whether an entity can perform computation and to what degree.",
      "reserved": false
    },
    {
      "index": 96,
      "name": "LegalEntity",
      "partition": "ontology",
      "description": "Indicates that an entity is recognized as a legal person or organization.",
      "reserved": false
    },
    {
      "index": 97,
      "name": "JurisdictionAnchor",
      "partition": "ontology",
      "description": "Anchors an entity or rule to a primary legal jurisdiction.",
      "reserved": false
    },
    {
      "index": 128,
      "name": "KnowledgeClaim",
      "partition": "ontology",
      "description": "Marks vectors that represent propositions or claims rather than concrete objects.",
      "reserved": false
    },
    {
      "index": 256,
      "name": "MoralValence",
      "partition": "axiology",
      "description": "Represents moral goodness or badness of an act or state.",
      "reserved": false
    },
    {
      "index": 280,
      "name": "UtilityValue",
      "partition": "axiology",
      "description": "Perceived utility or efficiency value associated with an action or state.",
      "reserved": false
    },
    {
      "index": 289,
      "name": "SafetyPreference",
      "partition": "axiology",
      "description": "Preference for safety over other objectives; high values indicate strong safety bias.",
      "reserved": false
    },
    {
      "index": 292,
      "name": "ReliabilityPreference",
      "partition": "axiology",
      "description": "Preference for reliable, robust behaviour over potentially fragile but efficient options.",
      "reserved": false
    },
    {
      "index": 294,
      "name": "TransparencyPreference",
      "partition": "axiology",
      "description": "Desire for transparent and explainable decisions rather than opaque ones.",
      "reserved": false
    },
    {
      "index": 297,
      "name": "IncentiveAlignment",
      "partition": "axiology",
      "description": "Measures how well incentives for different actors are aligned.",
      "reserved": false
    },
    {
      "index": 300,
      "name": "PrestigeValue",
      "partition": "axiology",
      "description": "Captures perceived prestige or status associated with an outcome.",
      "reserved": false
    },
    {
      "index": 320,
      "name": "EmotionFear",
      "partition": "axiology",
      "description": "Emotional dimension representing fear or anticipated danger.",
      "reserved": false
    },
    {
      "index": 323,
      "name": "EmotionJoy",
      "partition": "axiology",
      "description": "Emotional dimension representing joy or satisfaction.",
      "reserved": false
    },
    {
      "index": 326,
      "name": "EmpathyLevel",
      "partition": "axiology",
      "description": "Represents empathy or compassion felt toward affected entities.",
      "reserved": false
    },
    {
      "index": 328,
      "name": "TrustLevel",
      "partition": "axiology",
      "description": "Stores trust or confidence in an entity, process, or source.",
      "reserved": false
    },
    {
      "index": 384,
      "name": "EmpiricalLatent0",
      "partition": "empirical",
      "description": "First empirical latent axis reserved for learned features; semantics emerge from data.",
      "reserved": false
    }
  ],

  "propertyMappings": {
    "boiling_point": "Temperature",
    "temperature": "Temperature",
    "temp": "Temperature",
    "weight": "MassScale",
    "mass": "MassScale",
    "size": "SizeScale",
    "extent": "SizeScale",
    "age": "TemporalPersistence",
    "duration": "Duration",
    "frequency": "Frequency",
    "pressure": "Pressure",
    "density": "Density",
    "phase": "Phase"
  },

  "relationMappings": {
    "IS_A": ["Physicality", "Existence"],
    "IS_A_CERTAIN": ["Physicality", "Existence"],
    "IS_A_PROVEN": ["Physicality", "Existence"],
    "IS_A_POSSIBLE": ["Physicality", "Existence"],
    "IS_A_UNPROVEN": ["Physicality", "Existence"],

    "PART_OF": ["Mereological"],
    "HAS_PART": ["Mereological"],
    "CAUSES": ["CausalityStrength"],
    "CAUSED_BY": ["CausalityStrength"],
    "LOCATED_IN": ["LocationSpecificity"],
    "CONTAINS": ["LocationSpecificity"],
    "BEFORE": ["TemporalPersistence"],
    "AFTER": ["TemporalPersistence"],
    "PERMITS": ["MoralValence"],
    "PROHIBITS": ["MoralValence"],
    "OBLIGATES": ["MoralValence"],

    "IS_PHYSICAL": ["Physicality"],
    "IS_ABSTRACT": ["Physicality"],
    "WEIGHS": ["MassScale"],
    "HAS_SIZE": ["SizeScale"],
    "HAS_EXTENT": ["SpatialExtent"],
    "HAS_PHASE": ["Phase"],
    "IS_SOLID": ["Phase"],
    "IS_LIQUID": ["Phase"],
    "IS_GAS": ["Phase"],
    "HAS_PRESSURE": ["Pressure"],
    "LASTS": ["Duration"],
    "OCCURS_WITH_FREQUENCY": ["Frequency"],
    "IS_DETERMINISTIC": ["DeterminismLevel"],
    "IS_STOCHASTIC": ["DeterminismLevel"],
    "IS_REVERSIBLE": ["Reversibility"],
    "IS_IRREVERSIBLE": ["Reversibility"],

    "IS_LIVING": ["LivingStatus"],
    "IS_DEAD": ["LivingStatus"],
    "IS_INANIMATE": ["LivingStatus"],
    "BELONGS_TO_SPECIES": ["SpeciesTaxonomy"],
    "HAS_LIFE_STAGE": ["LifeStage"],
    "IS_JUVENILE": ["LifeStage"],
    "IS_ADULT": ["LifeStage"],
    "IS_SENESCENT": ["LifeStage"],
    "HAS_HEALTH": ["HealthVitality"],
    "IS_HEALTHY": ["HealthVitality"],
    "IS_SICK": ["HealthVitality"],

    "HAS_COGNITION": ["CognitionBaseline"],
    "IS_SAPIENT": ["CognitionBaseline"],
    "IS_SENTIENT": ["CognitionBaseline"],
    "IS_NON_SENTIENT": ["CognitionBaseline"],
    "HAS_AGENCY": ["AgencyBaseline"],
    "IS_AUTONOMOUS": ["AgencyBaseline"],
    "IS_ARTIFACT": ["ArtifactDevice"],
    "IS_NATURAL": ["ArtifactDevice"],
    "CAN_COMPUTE": ["ComputationCapability"],
    "IS_LEGAL_ENTITY": ["LegalEntity"],
    "UNDER_JURISDICTION": ["JurisdictionAnchor"],
    "IS_KNOWLEDGE_CLAIM": ["KnowledgeClaim"],
    "IS_PROPOSITION": ["KnowledgeClaim"],

    "IS_MORAL": ["MoralValence"],
    "IS_IMMORAL": ["MoralValence"],
    "IS_NEUTRAL": ["MoralValence"],
    "HAS_UTILITY": ["UtilityValue"],
    "IS_USEFUL": ["UtilityValue"],
    "IS_USELESS": ["UtilityValue"],
    "IS_SAFE": ["SafetyPreference"],
    "IS_DANGEROUS": ["SafetyPreference"],
    "IS_RELIABLE": ["ReliabilityPreference"],
    "IS_UNRELIABLE": ["ReliabilityPreference"],
    "IS_TRANSPARENT": ["TransparencyPreference"],
    "IS_OPAQUE": ["TransparencyPreference"],
    "HAS_ALIGNMENT": ["IncentiveAlignment"],
    "HAS_PRESTIGE": ["PrestigeValue"],

    "EVOKES_FEAR": ["EmotionFear"],
    "EVOKES_JOY": ["EmotionJoy"],
    "EVOKES_EMPATHY": ["EmpathyLevel"],
    "IS_TRUSTED": ["TrustLevel"],
    "IS_DISTRUSTED": ["TrustLevel"]
  },

  "partitions": {
    "computable": { "start": 16, "end": 31, "description": "Reserved dimensions for numeric values, units, and compute plugin metadata" },
    "ontology": { "start": 0, "end": 255, "excludes": [16, 17, 18, 19, 20, 21, 22, 23] },
    "axiology": { "start": 256, "end": 383 },
    "empirical": { "start": 384, "end": null }
  },

  "relationProperties": {
    "IS_A": { "transitive": true, "symmetric": false, "umbrella": true, "comment": "Umbrella relation - searches all existence variants and returns best" },
    "IS_A_CERTAIN": { "transitive": true, "symmetric": false, "existenceLevel": 127, "baseRelation": "IS_A" },
    "IS_A_PROVEN": { "transitive": true, "symmetric": false, "existenceLevel": 64, "baseRelation": "IS_A" },
    "IS_A_POSSIBLE": { "transitive": true, "symmetric": false, "existenceLevel": 0, "baseRelation": "IS_A" },
    "IS_A_UNPROVEN": { "transitive": true, "symmetric": false, "existenceLevel": -64, "baseRelation": "IS_A" },
    "PART_OF": { "transitive": true, "symmetric": false },
    "HAS_PART": { "transitive": true, "symmetric": false, "inverse": "PART_OF" },
    "ANCESTOR_OF": { "transitive": true, "symmetric": false },
    "LOCATED_IN": { "transitive": true, "symmetric": false },
    "CONTAINS": { "transitive": true, "symmetric": false, "inverse": "LOCATED_IN" },
    "REQUIRES": { "transitive": true, "symmetric": false },
    "EQUIVALENT_TO": { "transitive": true, "symmetric": true },
    "DISJOINT_WITH": { "transitive": false, "symmetric": true },
    "SIBLING_OF": { "transitive": false, "symmetric": true },
    "MARRIED_TO": { "transitive": false, "symmetric": true },
    "PARENT_OF": { "transitive": false, "symmetric": false, "inverse": "CHILD_OF" },
    "CHILD_OF": { "transitive": false, "symmetric": false, "inverse": "PARENT_OF" },
    "CAUSES": { "transitive": true, "symmetric": false, "inverse": "CAUSED_BY" },
    "CAUSED_BY": { "transitive": false, "symmetric": false, "inverse": "CAUSES" },
    "PERMITS": { "transitive": false, "symmetric": false, "inverse": "PERMITTED_BY" },
    "PERMITTED_BY": { "transitive": false, "symmetric": false, "inverse": "PERMITS" },
    "PROHIBITS": { "transitive": false, "symmetric": false, "inverse": "PROHIBITED_BY" },
    "PROHIBITED_BY": { "transitive": false, "symmetric": false, "inverse": "PROHIBITS" },
    "HAS_PROPERTY": { "transitive": false, "symmetric": false },

    "IS_PHYSICAL": { "transitive": false, "symmetric": false, "inheritable": true, "positioning": true, "targetValue": 127 },
    "IS_ABSTRACT": { "transitive": false, "symmetric": false, "inheritable": true, "positioning": true, "targetValue": -127 },
    "WEIGHS": { "transitive": false, "symmetric": false, "inheritable": true, "positioning": true },
    "HAS_SIZE": { "transitive": false, "symmetric": false, "inheritable": true, "positioning": true },
    "HAS_EXTENT": { "transitive": false, "symmetric": false, "inheritable": true, "positioning": true },
    "HAS_PHASE": { "transitive": false, "symmetric": false, "positioning": true },
    "IS_SOLID": { "transitive": false, "symmetric": false, "inheritable": true, "positioning": true, "targetValue": -100 },
    "IS_LIQUID": { "transitive": false, "symmetric": false, "inheritable": true, "positioning": true, "targetValue": 0 },
    "IS_GAS": { "transitive": false, "symmetric": false, "inheritable": true, "positioning": true, "targetValue": 100 },
    "HAS_PRESSURE": { "transitive": false, "symmetric": false, "inheritable": true, "positioning": true },
    "LASTS": { "transitive": false, "symmetric": false, "positioning": true },
    "OCCURS_WITH_FREQUENCY": { "transitive": false, "symmetric": false, "positioning": true },
    "IS_DETERMINISTIC": { "transitive": false, "symmetric": false, "inheritable": true, "positioning": true, "targetValue": 127 },
    "IS_STOCHASTIC": { "transitive": false, "symmetric": false, "inheritable": true, "positioning": true, "targetValue": -127 },
    "IS_REVERSIBLE": { "transitive": false, "symmetric": false, "inheritable": true, "positioning": true, "targetValue": 127 },
    "IS_IRREVERSIBLE": { "transitive": false, "symmetric": false, "inheritable": true, "positioning": true, "targetValue": -127 },

    "IS_LIVING": { "transitive": false, "symmetric": false, "inheritable": true, "positioning": true, "targetValue": 127 },
    "IS_DEAD": { "transitive": false, "symmetric": false, "positioning": true, "targetValue": -64 },
    "IS_INANIMATE": { "transitive": false, "symmetric": false, "inheritable": true, "positioning": true, "targetValue": -127 },
    "BELONGS_TO_SPECIES": { "transitive": false, "symmetric": false, "inheritable": true, "positioning": true },
    "HAS_LIFE_STAGE": { "transitive": false, "symmetric": false, "positioning": true },
    "IS_JUVENILE": { "transitive": false, "symmetric": false, "positioning": true, "targetValue": -64 },
    "IS_ADULT": { "transitive": false, "symmetric": false, "positioning": true, "targetValue": 64 },
    "IS_SENESCENT": { "transitive": false, "symmetric": false, "positioning": true, "targetValue": 127 },
    "HAS_HEALTH": { "transitive": false, "symmetric": false, "positioning": true },
    "IS_HEALTHY": { "transitive": false, "symmetric": false, "positioning": true, "targetValue": 127 },
    "IS_SICK": { "transitive": false, "symmetric": false, "positioning": true, "targetValue": -64 },

    "HAS_COGNITION": { "transitive": false, "symmetric": false, "inheritable": true, "positioning": true },
    "IS_SAPIENT": { "transitive": false, "symmetric": false, "inheritable": true, "positioning": true, "targetValue": 127 },
    "IS_SENTIENT": { "transitive": false, "symmetric": false, "inheritable": true, "positioning": true, "targetValue": 64 },
    "IS_NON_SENTIENT": { "transitive": false, "symmetric": false, "inheritable": true, "positioning": true, "targetValue": -127 },
    "HAS_AGENCY": { "transitive": false, "symmetric": false, "inheritable": true, "positioning": true },
    "IS_AUTONOMOUS": { "transitive": false, "symmetric": false, "inheritable": true, "positioning": true, "targetValue": 127 },
    "IS_ARTIFACT": { "transitive": false, "symmetric": false, "inheritable": true, "positioning": true, "targetValue": 127 },
    "IS_NATURAL": { "transitive": false, "symmetric": false, "inheritable": true, "positioning": true, "targetValue": -127 },
    "CAN_COMPUTE": { "transitive": false, "symmetric": false, "inheritable": true, "positioning": true },
    "IS_LEGAL_ENTITY": { "transitive": false, "symmetric": false, "positioning": true, "targetValue": 127 },
    "UNDER_JURISDICTION": { "transitive": false, "symmetric": false, "positioning": true },
    "IS_KNOWLEDGE_CLAIM": { "transitive": false, "symmetric": false, "positioning": true, "targetValue": 127 },
    "IS_PROPOSITION": { "transitive": false, "symmetric": false, "positioning": true, "targetValue": 64 },

    "IS_MORAL": { "transitive": false, "symmetric": false, "positioning": true, "targetValue": 127 },
    "IS_IMMORAL": { "transitive": false, "symmetric": false, "positioning": true, "targetValue": -127 },
    "IS_NEUTRAL": { "transitive": false, "symmetric": false, "positioning": true, "targetValue": 0 },
    "HAS_UTILITY": { "transitive": false, "symmetric": false, "inheritable": true, "positioning": true },
    "IS_USEFUL": { "transitive": false, "symmetric": false, "inheritable": true, "positioning": true, "targetValue": 127 },
    "IS_USELESS": { "transitive": false, "symmetric": false, "inheritable": true, "positioning": true, "targetValue": -127 },
    "IS_SAFE": { "transitive": false, "symmetric": false, "inheritable": true, "positioning": true, "targetValue": 127 },
    "IS_DANGEROUS": { "transitive": false, "symmetric": false, "inheritable": true, "positioning": true, "targetValue": -127 },
    "IS_RELIABLE": { "transitive": false, "symmetric": false, "inheritable": true, "positioning": true, "targetValue": 127 },
    "IS_UNRELIABLE": { "transitive": false, "symmetric": false, "inheritable": true, "positioning": true, "targetValue": -127 },
    "IS_TRANSPARENT": { "transitive": false, "symmetric": false, "inheritable": true, "positioning": true, "targetValue": 127 },
    "IS_OPAQUE": { "transitive": false, "symmetric": false, "inheritable": true, "positioning": true, "targetValue": -127 },
    "HAS_ALIGNMENT": { "transitive": false, "symmetric": false, "positioning": true },
    "HAS_PRESTIGE": { "transitive": false, "symmetric": false, "positioning": true },

    "EVOKES_FEAR": { "transitive": false, "symmetric": false, "positioning": true },
    "EVOKES_JOY": { "transitive": false, "symmetric": false, "positioning": true },
    "EVOKES_EMPATHY": { "transitive": false, "symmetric": false, "positioning": true },
    "IS_TRUSTED": { "transitive": false, "symmetric": false, "inheritable": true, "positioning": true, "targetValue": 127 },
    "IS_DISTRUSTED": { "transitive": false, "symmetric": false, "inheritable": true, "positioning": true, "targetValue": -127 },

    "HAS": { "transitive": false, "symmetric": false, "inheritable": true },
    "HELPS": { "transitive": false, "symmetric": false, "inheritable": true },
    "CAN": { "transitive": false, "symmetric": false, "inheritable": true },
    "PROVIDES": { "transitive": false, "symmetric": false, "inheritable": true },
    "DESIGNS": { "transitive": false, "symmetric": false, "inheritable": true },
    "PRODUCES": { "transitive": false, "symmetric": false, "inheritable": true },
    "BEFORE": { "transitive": true, "symmetric": false, "inverse": "AFTER", "computable": "datetime" },
    "AFTER": { "transitive": true, "symmetric": false, "inverse": "BEFORE", "computable": "datetime" },
    "LEADS_TO": { "transitive": true, "symmetric": false, "comment": "Step in derivation chain" },
    "SUBSET_OF": { "transitive": true, "symmetric": false },
    "MEMBER_OF": { "transitive": false, "symmetric": false, "comment": "Element belongs to set" },
    "PROVES": { "transitive": false, "symmetric": false, "comment": "Derivation chain proves conclusion" },
    "DERIVED_FROM": { "transitive": true, "symmetric": false, "comment": "Result origin" },
    "BECAUSE": { "transitive": false, "symmetric": false, "inverse": "EXPLAINS", "comment": "Causal explanation" },
    "EXPLAINS": { "transitive": false, "symmetric": false, "inverse": "BECAUSE" },
    "CONFLICTS_WITH": { "transitive": false, "symmetric": true, "comment": "Deontic/logical conflict" },
    "PERMITTED_TO": { "transitive": false, "symmetric": false, "contradicts": "PROHIBITED_FROM", "comment": "Deontic permission" },
    "PROHIBITED_FROM": { "transitive": false, "symmetric": false, "contradicts": "PERMITTED_TO", "comment": "Deontic prohibition" },
    "REQUIRED_TO": { "transitive": false, "symmetric": false, "comment": "Deontic obligation" },

    "LESS_THAN": { "transitive": true, "symmetric": false, "inverse": "GREATER_THAN", "computable": "math" },
    "GREATER_THAN": { "transitive": true, "symmetric": false, "inverse": "LESS_THAN", "computable": "math" },
    "EQUALS_VALUE": { "transitive": true, "symmetric": true, "computable": "math" },
    "PLUS": { "transitive": false, "symmetric": true, "computable": "math" },
    "MINUS": { "transitive": false, "symmetric": false, "computable": "math" },
    "TIMES": { "transitive": false, "symmetric": true, "computable": "math" },
    "DIVIDED_BY": { "transitive": false, "symmetric": false, "computable": "math" },
    "HAS_VALUE": { "transitive": false, "symmetric": false, "computable": "math" },

    "CONVERTS_TO": { "transitive": true, "symmetric": false, "computable": "physics" },
    "HAS_UNIT": { "transitive": false, "symmetric": false, "computable": "physics" },
    "HAS_TEMPERATURE": { "transitive": false, "symmetric": false, "computable": "physics" },
    "HAS_MASS": { "transitive": false, "symmetric": false, "computable": "physics" },
    "HAS_LENGTH": { "transitive": false, "symmetric": false, "computable": "physics" },
    "HAS_VOLUME": { "transitive": false, "symmetric": false, "computable": "physics" },
    "HAS_DENSITY": { "transitive": false, "symmetric": false, "computable": "physics" },
    "HAS_SPEED": { "transitive": false, "symmetric": false, "computable": "physics" },
    "HAS_FORCE": { "transitive": false, "symmetric": false, "computable": "physics" },
    "HAS_ENERGY": { "transitive": false, "symmetric": false, "computable": "physics" },
    "DENSITY_OF": { "transitive": false, "symmetric": false, "computable": "physics" },
    "SPEED_OF": { "transitive": false, "symmetric": false, "computable": "physics" },
    "FORCE_OF": { "transitive": false, "symmetric": false, "computable": "physics" },
    "ENERGY_OF": { "transitive": false, "symmetric": false, "computable": "physics" },

    "AND_WITH": { "transitive": false, "symmetric": true, "computable": "logic" },
    "OR_WITH": { "transitive": false, "symmetric": true, "computable": "logic" },
    "XOR_WITH": { "transitive": false, "symmetric": true, "computable": "logic" },
    "NOT_OF": { "transitive": false, "symmetric": false, "computable": "logic" },
    "IMPLIES": { "transitive": true, "symmetric": false, "computable": "logic" },
    "IFF": { "transitive": true, "symmetric": true, "computable": "logic" },
    "NAND_WITH": { "transitive": false, "symmetric": true, "computable": "logic" },
    "NOR_WITH": { "transitive": false, "symmetric": true, "computable": "logic" },
    "LOGICALLY_EQUIVALENT": { "transitive": true, "symmetric": true, "computable": "logic" },
    "CONTRADICTS": { "transitive": false, "symmetric": true, "computable": "logic" },
    "IS_SATISFIABLE": { "transitive": false, "symmetric": false, "computable": "logic" },
    "IS_TAUTOLOGY": { "transitive": false, "symmetric": false, "computable": "logic" },

    "SIMULTANEOUS_WITH": { "transitive": true, "symmetric": true, "computable": "datetime" },
    "OVERLAPS_WITH": { "transitive": false, "symmetric": true, "computable": "datetime" },
    "CONTAINS_TIME": { "transitive": true, "symmetric": false, "computable": "datetime" },
    "STARTS_WITH": { "transitive": false, "symmetric": true, "computable": "datetime" },
    "ENDS_WITH": { "transitive": false, "symmetric": true, "computable": "datetime" },
    "DURATION_BETWEEN": { "transitive": false, "symmetric": false, "computable": "datetime" },
    "AGE_OF": { "transitive": false, "symmetric": false, "computable": "datetime" },
    "ADD_DURATION": { "transitive": false, "symmetric": false, "computable": "datetime" },
    "SUBTRACT_DURATION": { "transitive": false, "symmetric": false, "computable": "datetime" },
    "DAY_OF_WEEK": { "transitive": false, "symmetric": false, "computable": "datetime" },
    "MONTH_OF": { "transitive": false, "symmetric": false, "computable": "datetime" },
    "YEAR_OF": { "transitive": false, "symmetric": false, "computable": "datetime" },
    "DURING": { "transitive": false, "symmetric": false, "computable": "datetime" }
  },

  "computePlugins": {
    "math": {
      "relations": ["LESS_THAN", "GREATER_THAN", "EQUALS_VALUE", "PLUS", "MINUS", "TIMES", "DIVIDED_BY", "HAS_VALUE"],
      "dimensions": ["NumericValue", "NumericScale"],
      "description": "Arithmetic operations and numeric comparisons"
    },
    "physics": {
      "relations": ["CONVERTS_TO", "HAS_UNIT", "HAS_TEMPERATURE", "HAS_MASS", "HAS_LENGTH", "HAS_VOLUME", "HAS_DENSITY", "HAS_SPEED", "HAS_FORCE", "HAS_ENERGY", "DENSITY_OF", "SPEED_OF", "FORCE_OF", "ENERGY_OF"],
      "dimensions": ["UnitDomain", "UnitBase", "UnitPrefix"],
      "description": "Unit conversions and physical calculations (temperature, mass, length, volume, speed, force, energy)"
    },
    "logic": {
      "relations": ["AND_WITH", "OR_WITH", "XOR_WITH", "NOT_OF", "IMPLIES", "IFF", "NAND_WITH", "NOR_WITH", "LOGICALLY_EQUIVALENT", "CONTRADICTS", "IS_SATISFIABLE", "IS_TAUTOLOGY"],
      "dimensions": [],
      "description": "Boolean and multi-valued logic operations (Kleene 3-valued logic extended to [-127, 127])"
    },
    "datetime": {
      "relations": ["BEFORE", "AFTER", "DURING", "SIMULTANEOUS_WITH", "OVERLAPS_WITH", "CONTAINS_TIME", "STARTS_WITH", "ENDS_WITH", "DURATION_BETWEEN", "AGE_OF", "ADD_DURATION", "SUBTRACT_DURATION", "DAY_OF_WEEK", "MONTH_OF", "YEAR_OF"],
      "dimensions": [],
      "description": "Temporal comparisons, duration calculations, and date arithmetic"
    }
  }
}
